{
  "sessions": [
    {
      "currency": "USD",
      "isVirtual": 1,
      "loginId": "VRTC1466549",
      "assetName": "R_100",
      "highestPrice": "11649.15",
      "lowestPrice": "11271.82",
      "tickDuration": 10,
      "startTime": "4/27/2017  3:15 pm",
      "endTime": "4/27/2017  3:48 pm",
      "startBalance": "7747.88",
      "balance": "7742.86",
      "profit": -5.020000000000437,
      "lossCap": -5,
      "profitCap": 5,
      "stake": 1,
      "winCount": 17,
      "lossCount": 0
    },
    {
      "currency": "USD",
      "isVirtual": 1,
      "loginId": "VRTC1466549",
      "assetName": "R_100",
      "highestPrice": "11550.02",
      "lowestPrice": "11271.82",
      "tickDuration": 10,
      "startTime": "4/27/2017  4:39 pm",
      "endTime": "4/27/2017  4:40 pm",
      "startBalance": "7741.26",
      "balance": "7742.20",
      "profit": 0.9399999999995998,
      "lossCap": -5,
      "profitCap": 5,
      "stake": 1,
      "winCount": 1,
      "lossCount": 0
    },
    {
      "currency": "USD",
      "isVirtual": 1,
      "loginId": "VRTC1466549",
      "assetName": "R_100",
      "highestPrice": "11559.27",
      "lowestPrice": "11271.82",
      "tickDuration": 10,
      "startTime": "4/27/2017  4:45 pm",
      "endTime": "4/27/2017  4:46 pm",
      "startBalance": "7743.14",
      "balance": "7744.08",
      "profit": 0.9399999999995998,
      "lossCap": -5,
      "profitCap": 5,
      "stake": 1,
      "winCount": 1,
      "lossCount": 0
    },
    {
      "currency": "USD",
      "isVirtual": 1,
      "loginId": "VRTC1466549",
      "assetName": "R_100",
      "highestPrice": "11613.37",
      "lowestPrice": "11271.82",
      "tickDuration": 10,
      "startTime": "4/27/2017  4:55 pm",
      "endTime": "4/27/2017  4:56 pm",
      "startBalance": "7744.08",
      "balance": "7743.08",
      "profit": -1,
      "lossCap": -5,
      "profitCap": 5,
      "stake": 1,
      "winCount": 0,
      "lossCount": 1
    },
    {
      "currency": "USD",
      "isVirtual": 1,
      "loginId": "VRTC1466549",
      "assetName": "R_100",
      "highestPrice": 0,
      "lowestPrice": 0,
      "tickDuration": 10,
      "startTime": "4/27/2017  4:56 pm",
      "endTime": "4/27/2017  4:57 pm",
      "startBalance": "7744.08",
      "balance": "7742.08",
      "profit": -2,
      "lossCap": -5,
      "profitCap": 5,
      "stake": 1,
      "winCount": 0,
      "lossCount": 1
    },
    {
      "currency": "USD",
      "isVirtual": 1,
      "loginId": "VRTC1466549",
      "assetName": "R_100",
      "highestPrice": "11619.05",
      "lowestPrice": "11271.82",
      "tickDuration": 10,
      "startTime": "4/27/2017  5:08 pm",
      "endTime": "4/27/2017  5:10 pm",
      "startBalance": "7741.08",
      "balance": "7742.02",
      "profit": 0.9400000000005093,
      "lossCap": -5,
      "profitCap": 5,
      "stake": 1,
      "winCount": 1,
      "lossCount": 0
    },
    {
      "currency": "USD",
      "isVirtual": 1,
      "loginId": "VRTC1466549",
      "assetName": "R_100",
      "highestPrice": 0,
      "lowestPrice": 0,
      "tickDuration": 10,
      "startTime": "4/27/2017  5:10 pm",
      "endTime": "4/27/2017  5:10 pm",
      "startBalance": "7741.08",
      "balance": "7742.96",
      "profit": 1.8800000000001091,
      "lossCap": -5,
      "profitCap": 5,
      "stake": 1,
      "winCount": 1,
      "lossCount": 0
    },
    {
      "currency": "USD",
      "isVirtual": 1,
      "loginId": "VRTC1466549",
      "assetName": "R_100",
      "highestPrice": 0,
      "lowestPrice": 0,
      "tickDuration": 10,
      "startTime": "4/27/2017  5:10 pm",
      "endTime": "4/27/2017  5:11 pm",
      "startBalance": "7741.08",
      "balance": "7743.90",
      "profit": 2.819999999999709,
      "lossCap": -5,
      "profitCap": 5,
      "stake": 1,
      "winCount": 1,
      "lossCount": 0
    },
    {
      "currency": "USD",
      "isVirtual": 1,
      "loginId": "VRTC1466549",
      "assetName": "R_100",
      "highestPrice": 0,
      "lowestPrice": 0,
      "tickDuration": 10,
      "startTime": "4/27/2017  5:11 pm",
      "endTime": "4/27/2017  5:11 pm",
      "startBalance": "7741.08",
      "balance": "7742.90",
      "profit": 1.819999999999709,
      "lossCap": -5,
      "profitCap": 5,
      "stake": 1,
      "winCount": 0,
      "lossCount": 1
    },
    {
      "currency": "USD",
      "isVirtual": 1,
      "loginId": "VRTC1466549",
      "assetName": "R_100",
      "highestPrice": "11579.65",
      "lowestPrice": "11207.34",
      "tickDuration": 10,
      "startTime": "4/27/2017  10:58 pm",
      "endTime": "4/27/2017  10:58 pm",
      "startBalance": "7586.52",
      "balance": "7585.52",
      "profit": -1,
      "lossCap": -5,
      "profitCap": 5,
      "stake": 1,
      "winCount": 0,
      "lossCount": 1
    },
    {
      "currency": "USD",
      "isVirtual": 1,
      "loginId": "VRTC1466549",
      "assetName": "R_100",
      "highestPrice": 0,
      "lowestPrice": 0,
      "tickDuration": 10,
      "startTime": "4/27/2017  10:58 pm",
      "endTime": "4/27/2017  10:59 pm",
      "startBalance": "7586.52",
      "balance": "7587.51",
      "profit": 0.9899999999997817,
      "lossCap": -5,
      "profitCap": 5,
      "stake": 1,
      "winCount": 1,
      "lossCount": 0
    },
    {
      "currency": "USD",
      "isVirtual": 1,
      "loginId": "VRTC1466549",
      "assetName": "R_100",
      "highestPrice": "11579.65",
      "lowestPrice": "11207.34",
      "tickDuration": 10,
      "startTime": "4/27/2017  11:21 pm",
      "endTime": "4/27/2017  11:22 pm",
      "startBalance": "7598.27",
      "balance": "7597.27",
      "profit": -1,
      "lossCap": -5,
      "profitCap": 5,
      "stake": 1,
      "winCount": 0,
      "lossCount": 1
    },
    {
      "currency": "USD",
      "isVirtual": 1,
      "loginId": "VRTC1466549",
      "assetName": "R_100",
      "highestPrice": 0,
      "lowestPrice": 0,
      "tickDuration": 10,
      "startTime": "4/27/2017  11:22 pm",
      "endTime": "4/27/2017  11:22 pm",
      "startBalance": "7598.27",
      "balance": "7599.26",
      "profit": 0.9899999999997817,
      "lossCap": -5,
      "profitCap": 5,
      "stake": 1,
      "winCount": 1,
      "lossCount": 0
    },
    {
      "currency": "USD",
      "isVirtual": 1,
      "loginId": "VRTC1466549",
      "assetName": "R_100",
      "highestPrice": "11579.65",
      "lowestPrice": "11207.34",
      "tickDuration": 10,
      "startTime": "4/27/2017  11:26 pm",
      "endTime": "4/27/2017  11:28 pm",
      "startBalance": "7606.15",
      "balance": "7607.09",
      "profit": 0.9400000000005093,
      "lossCap": -5,
      "profitCap": 5,
      "stake": 1,
      "winCount": 1,
      "lossCount": 0
    },
    {
      "currency": "USD",
      "isVirtual": 1,
      "loginId": "VRTC1466549",
      "assetName": "R_100",
      "highestPrice": "11579.65",
      "lowestPrice": "11207.34",
      "tickDuration": 10,
      "startTime": "4/27/2017  11:31 pm",
      "endTime": "4/27/2017  11:32 pm",
      "startBalance": "7607.09",
      "balance": "7606.09",
      "profit": -1,
      "lossCap": -5,
      "profitCap": 5,
      "stake": 1,
      "winCount": 0,
      "lossCount": 1
    },
    {
      "currency": "USD",
      "isVirtual": 1,
      "loginId": "VRTC1466549",
      "assetName": "R_100",
      "highestPrice": 0,
      "lowestPrice": 0,
      "tickDuration": 10,
      "startTime": "4/27/2017  11:32 pm",
      "endTime": "4/27/2017  11:33 pm",
      "startBalance": "7607.09",
      "balance": "7605.09",
      "profit": -2,
      "lossCap": -5,
      "profitCap": 5,
      "stake": 1,
      "winCount": 0,
      "lossCount": 1
    },
    {
      "currency": "USD",
      "isVirtual": 1,
      "loginId": "VRTC1466549",
      "assetName": "R_100",
      "highestPrice": "11576.01",
      "lowestPrice": "11207.34",
      "tickDuration": 10,
      "startTime": "4/27/2017  11:37 pm",
      "endTime": "4/27/2017  11:39 pm",
      "startBalance": "7610.09",
      "balance": "7609.09",
      "profit": -1,
      "lossCap": -5,
      "profitCap": 5,
      "stake": 1,
      "winCount": 0,
      "lossCount": 1
    },
    {
      "currency": "USD",
      "isVirtual": 1,
      "loginId": "VRTC1466549",
      "assetName": "R_100",
      "highestPrice": 0,
      "lowestPrice": 0,
      "tickDuration": 10,
      "startTime": "4/27/2017  11:39 pm",
      "endTime": "4/27/2017  11:39 pm",
      "startBalance": "7610.09",
      "balance": "7608.09",
      "profit": -2,
      "lossCap": -5,
      "profitCap": 5,
      "stake": 1,
      "winCount": 0,
      "lossCount": 1
    },
    {
      "currency": "USD",
      "isVirtual": 1,
      "loginId": "VRTC1466549",
      "assetName": "R_100",
      "highestPrice": "11498.05",
      "lowestPrice": "11207.34",
      "tickDuration": 10,
      "startTime": "4/27/2017  11:50 pm",
      "endTime": "4/27/2017  11:52 pm",
      "startBalance": "7493.36",
      "balance": "7494.30",
      "profit": 0.9400000000005093,
      "lossCap": -5,
      "profitCap": 5,
      "stake": 1,
      "winCount": 1,
      "lossCount": 0
    },
    {
      "currency": "USD",
      "isVirtual": 1,
      "loginId": "VRTC1466549",
      "assetName": "R_100",
      "highestPrice": 0,
      "lowestPrice": 0,
      "tickDuration": 10,
      "startTime": "4/27/2017  11:52 pm",
      "endTime": "4/27/2017  11:52 pm",
      "startBalance": "7493.36",
      "balance": "7493.30",
      "profit": -0.05999999999949068,
      "lossCap": -5,
      "profitCap": 5,
      "stake": 1,
      "winCount": 0,
      "lossCount": 1
    },
    {
      "currency": "USD",
      "isVirtual": 1,
      "loginId": "VRTC1466549",
      "assetName": "R_100",
      "highestPrice": 0,
      "lowestPrice": 0,
      "tickDuration": 10,
      "startTime": "4/27/2017  11:52 pm",
      "endTime": "4/27/2017  11:54 pm",
      "startBalance": "7493.36",
      "balance": "7494.24",
      "profit": 0.8800000000001091,
      "lossCap": -5,
      "profitCap": 5,
      "stake": 1,
      "winCount": 1,
      "lossCount": 0
    },
    {
      "currency": "USD",
      "isVirtual": 1,
      "loginId": "VRTC1466549",
      "assetName": "R_100",
      "highestPrice": "11485.31",
      "lowestPrice": "11207.34",
      "tickDuration": 10,
      "startTime": "4/27/2017  11:57 pm",
      "endTime": "4/28/2017  12:00 am",
      "lossCap": null,
      "profitCap": null
    },
    {
      "currency": "USD",
      "isVirtual": 1,
      "loginId": "VRTC1466549",
      "assetName": "R_100",
      "highestPrice": 0,
      "lowestPrice": 0,
      "tickDuration": 10,
      "startTime": "4/28/2017  12:00 am",
      "endTime": "4/28/2017  12:00 am",
      "lossCap": null,
      "profitCap": null
    },
    {
      "currency": "USD",
      "isVirtual": 1,
      "loginId": "VRTC1466549",
      "assetName": "R_100",
      "highestPrice": 0,
      "lowestPrice": 0,
      "tickDuration": 10,
      "startTime": "4/28/2017  12:00 am",
      "endTime": "4/28/2017  12:01 am",
      "lossCap": null,
      "profitCap": null
    }
  ]
}